data_grpc_service/__init__.py
data_grpc_service/protos/__init__.py
data_grpc_service/protos/detection_instance_data_api_pb2.py
data_grpc_service/protos/detection_instance_data_api_pb2_grpc.py
data_grpc_service/protos/image_data_api_pb2.py
data_grpc_service/protos/image_data_api_pb2_grpc.py
data_grpc_service/protos/protoc_gen_validate/validate_pb2.py
data_grpc_service/protos/protoc_gen_validate/validate_pb2_grpc.py
geospatial_toolkit_grpc_service/__init__.py
geospatial_toolkit_grpc_service/protos/__init__.py
geospatial_toolkit_grpc_service/protos/function_api_pb2.py
geospatial_toolkit_grpc_service/protos/function_api_pb2_grpc.py
geospatial_toolkit_grpc_service/protos/protoc_gen_validate/validate_pb2.py
geospatial_toolkit_grpc_service/protos/protoc_gen_validate/validate_pb2_grpc.py
global_vo_grpc_service/__init__.py
global_vo_grpc_service/protos/__init__.py
global_vo_grpc_service/protos/area_of_interest_api_pb2.py
global_vo_grpc_service/protos/area_of_interest_api_pb2_grpc.py
global_vo_grpc_service/protos/category_api_pb2.py
global_vo_grpc_service/protos/category_api_pb2_grpc.py
global_vo_grpc_service/protos/detection_api_pb2.py
global_vo_grpc_service/protos/detection_api_pb2_grpc.py
global_vo_grpc_service/protos/detection_instance_api_pb2.py
global_vo_grpc_service/protos/detection_instance_api_pb2_grpc.py
global_vo_grpc_service/protos/feature_api_pb2.py
global_vo_grpc_service/protos/feature_api_pb2_grpc.py
global_vo_grpc_service/protos/image_api_pb2.py
global_vo_grpc_service/protos/image_api_pb2_grpc.py
global_vo_grpc_service/protos/metric_api_pb2.py
global_vo_grpc_service/protos/metric_api_pb2_grpc.py
global_vo_grpc_service/protos/mission_api_pb2.py
global_vo_grpc_service/protos/mission_api_pb2_grpc.py
global_vo_grpc_service/protos/permission_api_pb2.py
global_vo_grpc_service/protos/permission_api_pb2_grpc.py
global_vo_grpc_service/protos/protoc_gen_validate/validate_pb2.py
global_vo_grpc_service/protos/protoc_gen_validate/validate_pb2_grpc.py
fsai_grpc_api-0.0.201.dist-info/METADATA
fsai_grpc_api-0.0.201.dist-info/WHEEL
fsai_grpc_api-0.0.201.dist-info/RECORD
